{
  "dashboard": {
    "id": null,
    "title": "Business Metrics",
    "tags": ["business", "metrics"],
    "style": "dark",
    "timezone": "browser",
    "refresh": "1m",
    "time": {
      "from": "now-24h",
      "to": "now"
    },
    "panels": [
      {
        "id": 1,
        "title": "Active Organizations",
        "type": "stat",
        "targets": [
          {
            "expr": "count(organizations_total)",
            "legendFormat": "Active Orgs"
          }
        ],
        "fieldConfig": {
          "defaults": {
            "color": {
              "mode": "palette-classic"
            },
            "custom": {
              "hideFrom": {
                "legend": false,
                "tooltip": false,
                "vis": false
              }
            },
            "mappings": [],
            "thresholds": {
              "mode": "absolute",
              "steps": [
                {
                  "color": "green",
                  "value": null
                }
              ]
            }
          }
        },
        "gridPos": {
          "h": 8,
          "w": 6,
          "x": 0,
          "y": 0
        }
      },
      {
        "id": 2,
        "title": "Posts Published Today",
        "type": "stat",
        "targets": [
          {
            "expr": "increase(posts_published_total[24h])",
            "legendFormat": "Posts Today"
          }
        ],
        "fieldConfig": {
          "defaults": {
            "color": {
              "mode": "palette-classic"
            },
            "custom": {
              "hideFrom": {
                "legend": false,
                "tooltip": false,
                "vis": false
              }
            },
            "mappings": [],
            "thresholds": {
              "mode": "absolute",
              "steps": [
                {
                  "color": "green",
                  "value": null
                }
              ]
            }
          }
        },
        "gridPos": {
          "h": 8,
          "w": 6,
          "x": 6,
          "y": 0
        }
      },
      {
        "id": 3,
        "title": "AI Generations Today",
        "type": "stat",
        "targets": [
          {
            "expr": "increase(ai_generations_total[24h])",
            "legendFormat": "AI Generations"
          }
        ],
        "fieldConfig": {
          "defaults": {
            "color": {
              "mode": "palette-classic"
            },
            "custom": {
              "hideFrom": {
                "legend": false,
                "tooltip": false,
                "vis": false
              }
            },
            "mappings": [],
            "thresholds": {
              "mode": "absolute",
              "steps": [
                {
                  "color": "green",
                  "value": null
                }
              ]
            }
          }
        },
        "gridPos": {
          "h": 8,
          "w": 6,
          "x": 12,
          "y": 0
        }
      },
      {
        "id": 4,
        "title": "Revenue Today",
        "type": "stat",
        "targets": [
          {
            "expr": "increase(revenue_total[24h])",
            "legendFormat": "Revenue ($)"
          }
        ],
        "fieldConfig": {
          "defaults": {
            "color": {
              "mode": "palette-classic"
            },
            "custom": {
              "hideFrom": {
                "legend": false,
                "tooltip": false,
                "vis": false
              }
            },
            "mappings": [],
            "thresholds": {
              "mode": "absolute",
              "steps": [
                {
                  "color": "green",
                  "value": null
                }
              ]
            },
            "unit": "currencyUSD"
          }
        },
        "gridPos": {
          "h": 8,
          "w": 6,
          "x": 18,
          "y": 0
        }
      },
      {
        "id": 5,
        "title": "Posts Published Over Time",
        "type": "timeseries",
        "targets": [
          {
            "expr": "rate(posts_published_total[1h])",
            "legendFormat": "Posts/hour"
          }
        ],
        "fieldConfig": {
          "defaults": {
            "color": {
              "mode": "palette-classic"
            },
            "custom": {
              "axisLabel": "",
              "axisPlacement": "auto",
              "barAlignment": 0,
              "drawStyle": "line",
              "fillOpacity": 0,
              "gradientMode": "none",
              "hideFrom": {
                "legend": false,
                "tooltip": false,
                "vis": false
              },
              "lineInterpolation": "linear",
              "lineWidth": 1,
              "pointSize": 5,
              "scaleDistribution": {
                "type": "linear"
              },
              "showPoints": "auto",
              "spanNulls": false,
              "stacking": {
                "group": "A",
                "mode": "none"
              },
              "thresholdsStyle": {
                "mode": "off"
              }
            },
            "mappings": [],
            "thresholds": {
              "mode": "absolute",
              "steps": [
                {
                  "color": "green",
                  "value": null
                }
              ]
            }
          }
        },
        "gridPos": {
          "h": 8,
          "w": 12,
          "x": 0,
          "y": 8
        }
      },
      {
        "id": 6,
        "title": "AI Usage Over Time",
        "type": "timeseries",
        "targets": [
          {
            "expr": "rate(ai_generations_total[1h])",
            "legendFormat": "AI Generations/hour"
          }
        ],
        "fieldConfig": {
          "defaults": {
            "color": {
              "mode": "palette-classic"
            },
            "custom": {
              "axisLabel": "",
              "axisPlacement": "auto",
              "barAlignment": 0,
              "drawStyle": "line",
              "fillOpacity": 0,
              "gradientMode": "none",
              "hideFrom": {
                "legend": false,
                "tooltip": false,
                "vis": false
              },
              "lineInterpolation": "linear",
              "lineWidth": 1,
              "pointSize": 5,
              "scaleDistribution": {
                "type": "linear"
              },
              "showPoints": "auto",
              "spanNulls": false,
              "stacking": {
                "group": "A",
                "mode": "none"
              },
              "thresholdsStyle": {
                "mode": "off"
              }
            },
            "mappings": [],
            "thresholds": {
              "mode": "absolute",
              "steps": [
                {
                  "color": "green",
                  "value": null
                }
              ]
            }
          }
        },
        "gridPos": {
          "h": 8,
          "w": 12,
          "x": 12,
          "y": 8
        }
      },
      {
        "id": 7,
        "title": "Revenue Over Time",
        "type": "timeseries",
        "targets": [
          {
            "expr": "rate(revenue_total[1h])",
            "legendFormat": "Revenue/hour ($)"
          }
        ],
        "fieldConfig": {
          "defaults": {
            "color": {
              "mode": "palette-classic"
            },
            "custom": {
              "axisLabel": "",
              "axisPlacement": "auto",
              "barAlignment": 0,
              "drawStyle": "line",
              "fillOpacity": 0,
              "gradientMode": "none",
              "hideFrom": {
                "legend": false,
                "tooltip": false,
                "vis": false
              },
              "lineInterpolation": "linear",
              "lineWidth": 1,
              "pointSize": 5,
              "scaleDistribution": {
                "type": "linear"
              },
              "showPoints": "auto",
              "spanNulls": false,
              "stacking": {
                "group": "A",
                "mode": "none"
              },
              "thresholdsStyle": {
                "mode": "off"
              }
            },
            "mappings": [],
            "thresholds": {
              "mode": "absolute",
              "steps": [
                {
                  "color": "green",
                  "value": null
                }
              ]
            },
            "unit": "currencyUSD"
          }
        },
        "gridPos": {
          "h": 8,
          "w": 12,
          "x": 0,
          "y": 16
        }
      },
      {
        "id": 8,
        "title": "User Engagement",
        "type": "timeseries",
        "targets": [
          {
            "expr": "rate(user_actions_total[1h])",
            "legendFormat": "Actions/hour"
          }
        ],
        "fieldConfig": {
          "defaults": {
            "color": {
              "mode": "palette-classic"
            },
            "custom": {
              "axisLabel": "",
              "axisPlacement": "auto",
              "barAlignment": 0,
              "drawStyle": "line",
              "fillOpacity": 0,
              "gradientMode": "none",
              "hideFrom": {
                "legend": false,
                "tooltip": false,
                "vis": false
              },
              "lineInterpolation": "linear",
              "lineWidth": 1,
              "pointSize": 5,
              "scaleDistribution": {
                "type": "linear"
              },
              "showPoints": "auto",
              "spanNulls": false,
              "stacking": {
                "group": "A",
                "mode": "none"
              },
              "thresholdsStyle": {
                "mode": "off"
              }
            },
            "mappings": [],
            "thresholds": {
              "mode": "absolute",
              "steps": [
                {
                  "color": "green",
                  "value": null
                }
              ]
            }
          }
        },
        "gridPos": {
          "h": 8,
          "w": 12,
          "x": 12,
          "y": 16
        }
      },
      {
        "id": 9,
        "title": "Plan Distribution",
        "type": "piechart",
        "targets": [
          {
            "expr": "count by (plan) (organizations_total)",
            "legendFormat": "{{plan}}"
          }
        ],
        "fieldConfig": {
          "defaults": {
            "color": {
              "mode": "palette-classic"
            },
            "custom": {
              "hideFrom": {
                "legend": false,
                "tooltip": false,
                "vis": false
              }
            },
            "mappings": [],
            "thresholds": {
              "mode": "absolute",
              "steps": [
                {
                  "color": "green",
                  "value": null
                }
              ]
            }
          }
        },
        "gridPos": {
          "h": 8,
          "w": 12,
          "x": 0,
          "y": 24
        }
      },
      {
        "id": 10,
        "title": "Channel Distribution",
        "type": "piechart",
        "targets": [
          {
            "expr": "count by (channel) (channels_connected_total)",
            "legendFormat": "{{channel}}"
          }
        ],
        "fieldConfig": {
          "defaults": {
            "color": {
              "mode": "palette-classic"
            },
            "custom": {
              "hideFrom": {
                "legend": false,
                "tooltip": false,
                "vis": false
              }
            },
            "mappings": [],
            "thresholds": {
              "mode": "absolute",
              "steps": [
                {
                  "color": "green",
                  "value": null
                }
              ]
            }
          }
        },
        "gridPos": {
          "h": 8,
          "w": 12,
          "x": 12,
          "y": 24
        }
      }
    ],
    "templating": {
      "list": []
    },
    "annotations": {
      "list": [
        {
          "builtIn": 1,
          "datasource": "-- Grafana --",
          "enable": true,
          "hide": true,
          "iconColor": "rgba(0, 211, 255, 1)",
          "name": "Annotations & Alerts",
          "type": "dashboard"
        }
      ]
    },
    "editable": true,
    "gnetId": null,
    "graphTooltip": 0,
    "links": [],
    "liveNow": false,
    "schemaVersion": 27,
    "version": 0
  }
}
